langchain_compressa/__init__.py
langchain_compressa/chat_models.py
langchain_compressa/embeddings.py
langchain_compressa/py.typed
langchain_compressa/reranks.py
langchain_compressa-0.1.4.dist-info/LICENSE
langchain_compressa-0.1.4.dist-info/METADATA
langchain_compressa-0.1.4.dist-info/WHEEL
langchain_compressa-0.1.4.dist-info/RECORD
