Metadata-Version: 2.1
Name: langchain-compressa
Version: 0.1.4
Summary: An integration package connecting Compressa and LangChain
Home-page: https://github.com/compressa-ai/langchain_compressa
License: MIT
Author: compressa.ai
Requires-Python: >=3.8.1,<4.0
Classifier: License :: OSI Approved :: MIT License
Classifier: Programming Language :: Python :: 3
Classifier: Programming Language :: Python :: 3.9
Classifier: Programming Language :: Python :: 3.10
Classifier: Programming Language :: Python :: 3.11
Classifier: Programming Language :: Python :: 3.12
Requires-Dist: filelock (>=3.15.1,<4.0.0)
Requires-Dist: langchain-core (>=0.3.5)
Requires-Dist: langchain-openai (>=0.2.0)
Requires-Dist: transformers (>=4.41.2,<5.0.0)
Project-URL: Repository, https://github.com/compressa-ai/langchain_compressa
Project-URL: Source Code, https://github.com/compressa-ai/langchain_compressa
